myfy/__init__.py
myfy/core/__init__.py
myfy/core/version.py
myfy/core/config/__init__.py
myfy/core/config/override.py
myfy/core/config/settings.py
myfy/core/di/__init__.py
myfy/core/di/container.py
myfy/core/di/errors.py
myfy/core/di/provider.py
myfy/core/di/scopes.py
myfy/core/di/types.py
myfy/core/kernel/__init__.py
myfy/core/kernel/app.py
myfy/core/kernel/errors.py
myfy/core/kernel/lifecycle.py
myfy/core/kernel/module.py
myfy_core-0.1.2.dist-info/METADATA
myfy_core-0.1.2.dist-info/WHEEL
myfy_core-0.1.2.dist-info/entry_points.txt
myfy_core-0.1.2.dist-info/RECORD
